xcn_translate/__init__.py
xcn_translate/sys.py
xcn_translate/webdriver.py
xcn_translate/Windows/__init__.py
xcn_translate/Windows/ping.py
xcn_translate/Windows/ps_util.py
xcn_translate/Windows/regstry.py
xcn_translate/Windows/xclog.py
xcn_translate/conf/__init__.py
xcn_translate/conf/folder.py
xcn_translate/conf/ini_file.py
xcn_translate/date/__init__.py
xcn_translate/date/str.py
xcn_translate/json/__init__.py
xcn_translate/json/dict.py
xcn_translate-0.0.16.dist-info/LICENSE
xcn_translate-0.0.16.dist-info/METADATA
xcn_translate-0.0.16.dist-info/WHEEL
xcn_translate-0.0.16.dist-info/top_level.txt
xcn_translate-0.0.16.dist-info/RECORD
