Metadata-Version: 2.2
Name: xcn_translate
Version: 0.0.16
Summary: some translate functions.
Home-page: https://github.com/pypa/sampleproject
Author: CMA
Author-email: cypressmobileapp@gmail.com
Project-URL: Bug Tracker, https://github.com/pypa/sampleproject/issues
Classifier: Programming Language :: Python :: 3
Classifier: License :: OSI Approved :: MIT License
Classifier: Operating System :: OS Independent
Requires-Python: >=3.7
License-File: LICENSE
Requires-Dist: coloredlogs==15.0.1
Requires-Dist: pythonping>=1.1.4
